{
  "base": "/images/sponsors",
  "sponsors": [
    {
      "name": "Atlassian",
      "imagePath": "/Atlassian.svg"
    },
    {
      "name": "Microsoft",
      "imagePath": "/Microsoft.svg"
    },
    {
      "name": "Google",
      "imagePath": "/Google.svg"
    },
    {
      "name": "Facebook",
      "imagePath": "/Facebook.svg"
    },
    {
      "name": "GitHub",
      "imagePath": "/GitHub.svg"
    },
    {
      "name": "PwC",
      "imagePath": "/PwC.svg"
    },
    {
      "name": "Telstra",
      "imagePath": "/Telstra.svg"
    },
    {
      "name": "Australia Post",
      "imagePath": "/Australia Post.svg"
    },
    {
      "name": "Xero",
      "imagePath": "/Xero.svg"
    },
    {
      "name": "Carsales",
      "imagePath": "/Carsales.svg"
    },

    {
      "name": "REA Group",
      "imagePath": "/REA Group.svg"
    },

    {
      "name": "Medipass",
      "imagePath": "/Medipass.svg"
    },

    {
      "name": "Twilio",
      "imagePath": "/Twilio.svg"
    },
    {
      "name": "Monash University",
      "imagePath": "/Monash University.svg"
    },
    {
      "name": "University of Melbourne",
      "imagePath": "/UniMelb.svg"
    }
  ]
}
