{
  "base": "/images/sponsors",
  "sponsors": [
    {
      "name": "Facebook",
      "imagePath": "/facebook.png"
    },
    {
      "name": "Atlassian",
      "imagePath": "/atlassian.png"
    },
    {
      "name": "Microsoft",
      "imagePath": "/microsoft.png"
    },
    {
      "name": "Bosch",
      "imagePath": "/bosch.png"
    },
    {
      "name": "Xero",
      "imagePath": "/xero.png"
    },
    {
      "name": "REA Group",
      "imagePath": "/rea.png"
    },
    {
      "name": "Telstra",
      "imagePath": "/telstra.png"
    },
    {
      "name": "Accenture",
      "imagePath": "/accenture.png"
    },
    {
      "name": "PwC",
      "imagePath": "/pwc.png"
    },
    {
      "name": "Infosys",
      "imagePath": "/infosys.png"
    },
    {
      "name": "GitHub",
      "imagePath": "/github.png"
    },
    {
      "name": "Adobe",
      "imagePath": "/adobe.png"
    },
    {
      "name": "Data61",
      "imagePath": "/data61.png"
    },
    {
      "name": "University of Melbourne",
      "imagePath": "/unimelb.png"
    },
    {
      "name": "Monash University",
      "imagePath": "/monash.png"
    }
  ]
}
